jsoneditor/__init__.py
jsoneditor/admin.py
jsoneditor/forms.py
jsoneditor/static/jsoneditor/jsoneditor.map
jsoneditor/static/jsoneditor/jsoneditor.min.css
jsoneditor/static/jsoneditor/jsoneditor.min.js
jsoneditor/static/jsoneditor/img/jsoneditor-icons.svg
jsoneditor/templates/jsoneditor/jsoneditor.html
django_jsoneditor_widget-1.3.2.dist-info/LICENSE
django_jsoneditor_widget-1.3.2.dist-info/METADATA
django_jsoneditor_widget-1.3.2.dist-info/WHEEL
django_jsoneditor_widget-1.3.2.dist-info/top_level.txt
django_jsoneditor_widget-1.3.2.dist-info/RECORD
