Metadata-Version: 2.1
Name: django-jsoneditor-widget
Version: 1.3.2
Summary: Django form widget form JSONField
Home-page: https://github.com/arthurc0102/django-jsoneditor-widget
Author: Arthur Chang
Author-email: arthurc0102@gmail.com
License: MIT
Platform: UNKNOWN
